sunwaee/api.py
sunwaee/cli.py
sunwaee/helpers.py
sunwaee/logger.py
sunwaee/gen/__init__.py
sunwaee/gen/agent.py
sunwaee/gen/message.py
sunwaee/gen/model.py
sunwaee/gen/provider.py
sunwaee/gen/response.py
sunwaee/gen/tool.py
sunwaee/gen/tool_call.py
sunwaee/gen/_api/__init__.py
sunwaee/gen/_api/_router.py
sunwaee/gen/_api/agents.py
sunwaee/gen/_api/completion.py
sunwaee/gen/_api/models.py
sunwaee/gen/_api/providers.py
sunwaee/gen/_cli/__init__.py
sunwaee/gen/_cli/_entrypoint.py
sunwaee/gen/_cli/list.py
sunwaee/gen/_cli/serve.py
sunwaee/gen/agents/__init__.py
sunwaee/gen/agents/_registry.py
sunwaee/gen/agents/anthropic.py
sunwaee/gen/agents/deepseek.py
sunwaee/gen/agents/google.py
sunwaee/gen/agents/openai.py
sunwaee/gen/agents/xai.py
sunwaee/gen/models/__init__.py
sunwaee/gen/models/_registry.py
sunwaee/gen/models/anthropic.py
sunwaee/gen/models/deepseek.py
sunwaee/gen/models/google.py
sunwaee/gen/models/openai.py
sunwaee/gen/models/xai.py
sunwaee/gen/providers/__init__.py
sunwaee/gen/providers/_registry.py
sunwaee/gen/providers/anthropic.py
sunwaee/gen/providers/deepseek.py
sunwaee/gen/providers/google.py
sunwaee/gen/providers/openai.py
sunwaee/gen/providers/xai.py
sunwaee-0.0.6.dist-info/licenses/LICENSE
sunwaee-0.0.6.dist-info/METADATA
sunwaee-0.0.6.dist-info/WHEEL
sunwaee-0.0.6.dist-info/entry_points.txt
sunwaee-0.0.6.dist-info/top_level.txt
sunwaee-0.0.6.dist-info/RECORD
